gender_extractor/__init__.py
gender_extractor/extractor.py
gender_extractor/nameLists/AfghanistanFemaleUTF8.csv
gender_extractor/nameLists/AfghanistanMaleUTF8.csv
gender_extractor/nameLists/AlbaniaFemaleUTF8.csv
gender_extractor/nameLists/AlbaniaMaleUTF8.csv
gender_extractor/nameLists/AustraliaFemaleUTF8.csv
gender_extractor/nameLists/AustraliaMaleUTF8.csv
gender_extractor/nameLists/BelgiumFemaleUTF8.csv
gender_extractor/nameLists/BelgiumMaleUTF8.csv
gender_extractor/nameLists/BrazilFemaleUTF8.csv
gender_extractor/nameLists/BrazilMaleUTF8.csv
gender_extractor/nameLists/BrusselsFemaleUTF8.csv
gender_extractor/nameLists/BrusselsMaleUTF8.csv
gender_extractor/nameLists/CanadaFemaleUTF8.csv
gender_extractor/nameLists/CanadaMaleUTF8.csv
gender_extractor/nameLists/CzechFemaleUTF8.csv
gender_extractor/nameLists/CzechMaleUTF8.csv
gender_extractor/nameLists/FinlandFemaleUTF8.csv
gender_extractor/nameLists/FinlandMaleUTF8.csv
gender_extractor/nameLists/FlandersFemaleUTF8.csv
gender_extractor/nameLists/FlandersMaleUTF8.csv
gender_extractor/nameLists/FrisiaFemaleUTF8.csv
gender_extractor/nameLists/FrisiaMaleUTF8.csv
gender_extractor/nameLists/GreeceFemaleUTF8.csv
gender_extractor/nameLists/GreeceMaleUTF8.csv
gender_extractor/nameLists/HungaryFemaleUTF8.csv
gender_extractor/nameLists/HungaryMaleUTF8.csv
gender_extractor/nameLists/IndiaFemaleUTF8.csv
gender_extractor/nameLists/IndiaLastNames.csv
gender_extractor/nameLists/IndiaMaleUTF8.csv
gender_extractor/nameLists/IranFemaleUTF8.csv
gender_extractor/nameLists/IranMaleUTF8.csv
gender_extractor/nameLists/IrelandFemaleUTF8.csv
gender_extractor/nameLists/IrelandMaleUTF8.csv
gender_extractor/nameLists/IsraelFemaleUTF8.csv
gender_extractor/nameLists/IsraelMaleUTF8.csv
gender_extractor/nameLists/ItalyFemaleUTF8.csv
gender_extractor/nameLists/ItalyMaleUTF8.csv
gender_extractor/nameLists/JapanFemaleUTF8.csv
gender_extractor/nameLists/JapanMaleUTF8.csv
gender_extractor/nameLists/LatviaFemaleUTF8.csv
gender_extractor-0.1.3.dist-info/LICENSE
gender_extractor-0.1.3.dist-info/METADATA
gender_extractor-0.1.3.dist-info/WHEEL
gender_extractor-0.1.3.dist-info/top_level.txt
gender_extractor-0.1.3.dist-info/RECORD
