Metadata-Version: 2.1
Name: gender-extractor
Version: 0.1.3
Summary: Extract the suspected gender given a name
Home-page: https://github.com/wwydmanski/gender-extractor
Author: Witold Wydmański
Author-email: witold.wydmanski@uj.edu.pl
License: MIT
Platform: UNKNOWN
Classifier: License :: OSI Approved :: MIT License
Classifier: Programming Language :: Python :: 3
Classifier: Programming Language :: Python :: 3.7
